{
 "SoundBanksInfo": {
  "Platform": "Windows",
  "BasePlatform": "Windows",
  "SchemaVersion": "16",
  "SoundBankVersion": "154",
  "SoundBanks": [
   {
    "Id": "1290008370",
    "Type": "User",
    "GUID": "{82E2EF59-3589-4F2A-A6D8-5CAECE37D4D5}",
    "Language": "SFX",
    "Hash": "{B91A589E-9111-A47E-93D6-213271750FC0}",
    "ObjectPath": "\\SoundBanks\\Default Work Unit\\Level_2",
    "ShortName": "Level_2",
    "Path": "Level_2.bnk",
    "Media": [
     {
      "Id": "346857431",
      "Language": "SFX",
      "Streaming": "false",
      "Location": "Memory",
      "ShortName": "Mill_1.wav",
      "CachePath": "A3/{A3B3B217-EB14-F71F-D15B-D44CD120697B}.wem"
     },
     {
      "Id": "721682378",
      "Language": "SFX",
      "Streaming": "false",
      "Location": "Memory",
      "ShortName": "LVL_2.wav",
      "CachePath": "6A/{6AE078F8-3334-D7ED-37F3-890870D6E4DC}.wem"
     }
    ],
    "Events": [
     {
      "Id": "2152580027",
      "Name": "Play_LVL_2",
      "ObjectPath": "\\Events\\Default Work Unit\\Music\\LVL_2\\Play_LVL_2",
      "GUID": "{A03D770D-BAF7-40D3-8261-DE8AB1FBC87F}",
      "DurationType": "Infinite",
      "MediaRefs": [
       {
        "Id": "721682378"
       }
      ]
     },
     {
      "Id": "3773477196",
      "Name": "Play_Mill_1",
      "ObjectPath": "\\Events\\Default Work Unit\\SFX\\Mill\\Play_Mill_1",
      "GUID": "{0E785823-EAF8-41E1-B562-855F5F90C23D}",
      "MaxAttenuation": "15",
      "DurationType": "Infinite",
      "MediaRefs": [
       {
        "Id": "346857431"
       }
      ]
     },
     {
      "Id": "2647050345",
      "Name": "Stop_LVL_2",
      "ObjectPath": "\\Events\\Default Work Unit\\Music\\LVL_2\\Stop_LVL_2",
      "GUID": "{4F8C9F9C-2C40-465C-A955-45162741A9E9}",
      "MaxAttenuation": "0",
      "DurationType": "OneShot",
      "DurationMin": "0",
      "DurationMax": "0"
     },
     {
      "Id": "3495523558",
      "Name": "Stop_Mill_1",
      "ObjectPath": "\\Events\\Default Work Unit\\SFX\\Mill\\Stop_Mill_1",
      "GUID": "{C0A976E4-773E-46EA-AAED-7772CD129AAB}",
      "MaxAttenuation": "0",
      "DurationType": "OneShot",
      "DurationMin": "0",
      "DurationMax": "0"
     }
    ]
   }
  ],
  "FileHash": "{DB4372F9-6434-3734-0371-2F0E1DB4055C}"
 }
}